{
  "tasks": [
    {
      "id": "1",
      "title": "Prepare presentation",
      "description": "Prepare slides for Monday's meeting",
      "dueDate": "2024-12-15",
      "priority": "High",
      "status": "In Progress"
    },
    {
      "id": "2",
      "title": "Submit report",
      "description": "Submit the financial report for Q4",
      "dueDate": "2024-12-20",
      "priority": "Medium",
      "status": "Pending"
    },
    {
      "id": "3",
      "title": "Team feedback",
      "description": "Collect feedback from the team on the new process",
      "dueDate": "2024-12-18",
      "priority": "Low",
      "status": "Completed"
    }
  ],
  "subtasks": [
    { "id": "1", "text": "Draft introduction", "taskId": "1" },
    { "id": "2", "text": "Add graphics", "taskId": "1" },
    { "id": "3", "text": "Review calculations", "taskId": "2" }
  ],
  "user": {
    "name": "Task Manager"
  }
}
